{
  "key": 159516067,
  "nubKey": 7595433,
  "nameKey": 10016231,
  "taxonID": "53467",
  "kingdom": "Animalia",
  "phylum": "Chordata",
  "order": "Salmoniformes",
  "family": "Salmonidae",
  "genus": "Salmo",
  "species": "Salmo salar",
  "kingdomKey": 196502841,
  "phylumKey": 196508488,
  "classKey": 196509182,
  "orderKey": 196509224,
  "familyKey": 196509226,
  "genusKey": 196509233,
  "speciesKey": 159516067,
  "datasetKey": "39f36f10-559b-427f-8c86-2d28afff68ca",
  "parentKey": 196509233,
  "parent": "Salmo",
  "scientificName": "Salmo salar",
  "canonicalName": "Salmo salar",
  "vernacularName": "Sebago (landlocked) Salmon",
  "authorship": "",
  "nameType": "SCIENTIFIC",
  "rank": "SPECIES",
  "origin": "SOURCE",
  "taxonomicStatus": "ACCEPTED",
  "nomenclaturalStatus": [],
  "remarks": "Navajas M et al. (2010) Mites and ticks (Acari). Chapter 7.4. In: Roques A et al. (Eds) Arthropod invasions in Europe. BioRisk 4(1): 149\u2013192.",
  "numDescendants": 0,
  "lastCrawled": "2023-08-24T11:02:18.435+00:00",
  "lastInterpreted": "2022-07-08T23:03:07.372+00:00",
  "issues": [],
  "class": "Actinopterygii"
}